jax_models/__init__.py
jax_models/activations/__init__.py
jax_models/activations/activations.py
jax_models/initializers/__init__.py
jax_models/initializers/initializers.py
jax_models/layers/__init__.py
jax_models/layers/attention.py
jax_models/layers/depthwise_separable_conv.py
jax_models/layers/drop.py
jax_models/layers/mask.py
jax_models/layers/mlp.py
jax_models/layers/patch_util.py
jax_models/layers/pool.py
jax_models/layers/squeeze_and_excite_layer.py
jax_models/models/__init__.py
jax_models/models/cait.py
jax_models/models/conv_mixer.py
jax_models/models/convnext.py
jax_models/models/helper.py
jax_models/models/masked_autoencoder.py
jax_models/models/mlp_mixer.py
jax_models/models/model_registry.py
jax_models/models/mpvit.py
jax_models/models/patchconvnet.py
jax_models/models/poolformer.py
jax_models/models/pvit.py
jax_models/models/segformer.py
jax_models/models/swin_transformer.py
jax_models/models/van.py
jax_models-0.0.5.dist-info/LICENSE
jax_models-0.0.5.dist-info/METADATA
jax_models-0.0.5.dist-info/WHEEL
jax_models-0.0.5.dist-info/top_level.txt
jax_models-0.0.5.dist-info/RECORD
