Metadata-Version: 2.1
Name: jax-models
Version: 0.0.5
Summary: Unofficial JAX implementations of deep learning research papers
Home-page: https://github.com/darshandeshpande/jax-models
Author: Darshan Deshpande
Author-email: darshan.g.deshpande@gmail.com
License: UNKNOWN
Keywords: jax flax models computer-vision deep-learning transformers
Platform: UNKNOWN
Classifier: Development Status :: 3 - Alpha
Classifier: Intended Audience :: Education
Classifier: Intended Audience :: Science/Research
Classifier: License :: OSI Approved :: Apache Software License
Classifier: Programming Language :: Python :: 3.6
Classifier: Programming Language :: Python :: 3.7
Classifier: Programming Language :: Python :: 3.8
Classifier: Programming Language :: Python :: 3.9
Classifier: Topic :: Scientific/Engineering
Classifier: Topic :: Scientific/Engineering :: Artificial Intelligence
Classifier: Topic :: Software Development
Classifier: Topic :: Software Development :: Libraries
Classifier: Topic :: Software Development :: Libraries :: Python Modules
Requires-Python: >=3.6
License-File: LICENSE
Requires-Dist: flax (>=0.3.6)
Requires-Dist: tqdm
